{
  "kind": "singleType",
  "collectionName": "nvme_dedicated_server_page",
  "info": {
    "singularName": "nvme-dedicated-server-page",
    "pluralName": "nvme-dedicated-server-pages",
    "displayName": "NVMe Dedicated Server Page",
    "description": "Content for the NVMe Dedicated Servers page"
  },
  "options": { "draftAndPublish": true },
  "pluginOptions": {},
  "attributes": {
    "seo": { "type": "component", "repeatable": false, "component": "shared.seo" },
    "heroEyebrow": { "type": "string" },
    "heroTitle": { "type": "string", "required": true },
    "heroSubtitle": { "type": "string" },
    "heroDescription": { "type": "text" },
    "heroTopBadge": { "type": "string" },
    "heroStatusTitle": { "type": "string" },
    "heroStatusSubtitle": { "type": "string" },
    "heroCtaPrimary": { "type": "component", "repeatable": false, "component": "shared.cta-button" },
    "heroCtaSecondary": { "type": "component", "repeatable": false, "component": "shared.cta-button" },
    "pillars": { "type": "component", "repeatable": true, "component": "shared.icon-card" },
    "plansLabel": { "type": "string" },
    "plansTitle": { "type": "string" },
    "plansSubtitle": { "type": "text" },
    "plans": { "type": "component", "repeatable": true, "component": "shared.pricing-plan" },
    "infraLabel": { "type": "string" },
    "infraTitle": { "type": "string" },
    "infraSubtitle": { "type": "text" },
    "infraFeatures": { "type": "component", "repeatable": true, "component": "shared.icon-card" },
    "whyNvmeLabel": { "type": "string" },
    "whyNvmeTitle": { "type": "string" },
    "whyNvmeSubtitle": { "type": "text" },
    "whyNvmeCards": { "type": "component", "repeatable": true, "component": "shared.icon-card" },
    "useCasesLabel": { "type": "string" },
    "useCasesTitle": { "type": "string" },
    "useCasesSubtitle": { "type": "text" },
    "useCases": { "type": "component", "repeatable": true, "component": "shared.icon-card" },
    "whenLabel": { "type": "string" },
    "whenTitle": { "type": "string" },
    "whenSubtitle": { "type": "text" },
    "whenCards": { "type": "component", "repeatable": true, "component": "shared.numbered-step" },
    "ctaBand2": { "type": "component", "repeatable": false, "component": "shared.cta-band" },
    "testimonialTitle": { "type": "string" },
    "testimonials": { "type": "component", "repeatable": true, "component": "shared.testimonial" },
    "faqTitle": { "type": "string" },
    "faqContactTitle": { "type": "string" },
    "faqContactDesc": { "type": "text" },
    "faq": { "type": "component", "repeatable": true, "component": "shared.faq-item" }
  }
}
